as_flask_docs/__init__.py
as_flask_docs/error.py
as_flask_docs/models.py
as_flask_docs/openapi.py
as_flask_docs/schema.py
as_flask_docs/templates/rapidoc.html
as_flask_docs/templates/redoc.html
as_flask_docs/templates/swagger.html
as_flask_docs/utils.py
as_flask_docs-1.0.5.dist-info/LICENSE
as_flask_docs-1.0.5.dist-info/METADATA
as_flask_docs-1.0.5.dist-info/WHEEL
as_flask_docs-1.0.5.dist-info/RECORD
