Metadata-Version: 2.1
Name: as-flask-docs
Version: 1.0.5
Summary: 对flask提供数据校验和openapi(swagger)文档自动生成的支持
Home-page: https://github.com/Dorain-An/flask-docs
Keywords: flask,api,docs,swagger,redoc,rapidoc
Author: liuzhijun
Author-email: lzjun567@gmail.com
Maintainer: ansen
Maintainer-email: ansen921@gmail.com
Requires-Python: >=3.7,<4.0
Classifier: Programming Language :: Python :: 3
Classifier: Programming Language :: Python :: 3.7
Classifier: Programming Language :: Python :: 3.8
Classifier: Programming Language :: Python :: 3.9
Classifier: Programming Language :: Python :: 3.10
Classifier: Programming Language :: Python :: 3.11
Requires-Dist: Flask (>=2.0.2,<3.0.0)
Requires-Dist: pydantic (>=1.9.0,<2.0.0)
